[{"player": "FengF", "org": "TE", "rounds": "336", "rating": "", "average_combat_score": "253.2", "kill_deaths": "1.18", "kill_assists_survived_traded": "", "average_damage_per_round": "", "kills_per_round": "0.84", "assists_per_round": "0.29", "first_kills_per_round": "", "first_deaths_per_round": "", "headshot_percentage": "", "clutch_success_percentage": "", "agents_played": ["sova", "raze", "cypher"], "kmax": "40", "kills": "283", "deaths": "240", "assists": "98", "fk": "0", "fd": "0"}, {"player": "Biank", "org": "BLG", "rounds": "202", "rating": "", "average_combat_score": "191.4", "kill_deaths": "0.88", "kill_assists_survived_traded": "", "average_damage_per_round": "", "kills_per_round": "0.62", "assists_per_round": "0.30", "first_kills_per_round": "", "first_deaths_per_round": "", "headshot_percentage": "", "clutch_success_percentage": "", "agents_played": ["sova", "fade", "skye"], "kmax": "19", "kills": "126", "deaths": "143", "assists": "61", "fk": "0", "fd": "0"}, {"player": "Nicc", "org": "DRG", "rounds": "151", "rating": "", "average_combat_score": "195.9", "kill_deaths": "1.04", "kill_assists_survived_traded": "", "average_damage_per_round": "", "kills_per_round": "0.71", "assists_per_round": "0.44", "first_kills_per_round": "", "first_deaths_per_round": "", "headshot_percentage": "", "clutch_success_percentage": "", "agents_played": ["breach", "kayo", "gekko"], "kmax": "21", "kills": "107", "deaths": "103", "assists": "67", "fk": "0", "fd": "0"}, {"player": "TvirusLuke", "org": "DRG", "rounds": "151", "rating": "", "average_combat_score": "205.9", "kill_deaths": "0.79", "kill_assists_survived_traded": "", "average_damage_per_round": "", "kills_per_round": "0.66", "assists_per_round": "0.20", "first_kills_per_round": "", "first_deaths_per_round": "", "headshot_percentage": "", "clutch_success_percentage": "", "agents_played": ["neon", "jett", "raze"], "kmax": "21", "kills": "99", "deaths": "126", "assists": "30", "fk": "0", "fd": "0"}, {"player": "vo0kashu", "org": "DRG", "rounds": "151", "rating": "", "average_combat_score": "248.9", "kill_deaths": "1.18", "kill_assists_survived_traded": "", "average_damage_per_round": "", "kills_per_round": "0.87", "assists_per_round": "0.28", "first_kills_per_round": "", "first_deaths_per_round": "", "headshot_percentage": "", "clutch_success_percentage": "", "agents_played": ["cypher", "killjoy"], "kmax": "27", "kills": "132", "deaths": "112", "assists": "42", "fk": "0", "fd": "0"}, {"player": "Dingwei", "org": "DRG", "rounds": "151", "rating": "", "average_combat_score": "160.1", "kill_deaths": "0.77", "kill_assists_survived_traded": "", "average_damage_per_round": "", "kills_per_round": "0.54", "assists_per_round": "0.30", "first_kills_per_round": "", "first_deaths_per_round": "", "headshot_percentage": "", "clutch_success_percentage": "", "agents_played": ["sova", "skye", "viper"], "kmax": "18", "kills": "82", "deaths": "107", "assists": "45", "fk": "0", "fd": "0"}, {"player": "nizhaoTZH", "org": "DRG", "rounds": "151", "rating": "", "average_combat_score": "192.1", "kill_deaths": "1.06", "kill_assists_survived_traded": "", "average_damage_per_round": "", "kills_per_round": "0.72", "assists_per_round": "0.38", "first_kills_per_round": "", "first_deaths_per_round": "", "headshot_percentage": "", "clutch_success_percentage": "", "agents_played": ["omen", "viper", "brimstone"], "kmax": "22", "kills": "108", "deaths": "102", "assists": "57", "fk": "0", "fd": "0"}, {"player": "sword9", "org": "AG", "rounds": "86", "rating": "", "average_combat_score": "161.0", "kill_deaths": "0.75", "kill_assists_survived_traded": "", "average_damage_per_round": "", "kills_per_round": "0.53", "assists_per_round": "0.31", "first_kills_per_round": "", "first_deaths_per_round": "", "headshot_percentage": "", "clutch_success_percentage": "", "agents_played": ["sova", "kayo"], "kmax": "13", "kills": "46", "deaths": "61", "assists": "27", "fk": "0", "fd": "0"}, {"player": "bunt", "org": "AG", "rounds": "86", "rating": "", "average_combat_score": "240.5", "kill_deaths": "1.17", "kill_assists_survived_traded": "", "average_damage_per_round": "", "kills_per_round": "0.87", "assists_per_round": "0.34", "first_kills_per_round": "", "first_deaths_per_round": "", "headshot_percentage": "", "clutch_success_percentage": "", "agents_played": ["omen", "viper"], "kmax": "28", "kills": "75", "deaths": "64", "assists": "29", "fk": "0", "fd": "0"}, {"player": "monk", "org": "AG", "rounds": "86", "rating": "", "average_combat_score": "189.3", "kill_deaths": "0.83", "kill_assists_survived_traded": "", "average_damage_per_round": "", "kills_per_round": "0.66", "assists_per_round": "0.19", "first_kills_per_round": "", "first_deaths_per_round": "", "headshot_percentage": "", "clutch_success_percentage": "", "agents_played": ["breach", "killjoy", "harbor"], "kmax": "18", "kills": "57", "deaths": "69", "assists": "16", "fk": "0", "fd": "0"}, {"player": "deLb", "org": "AG", "rounds": "86", "rating": "", "average_combat_score": "188.5", "kill_deaths": "0.83", "kill_assists_survived_traded": "", "average_damage_per_round": "", "kills_per_round": "0.64", "assists_per_round": "0.17", "first_kills_per_round": "", "first_deaths_per_round": "", "headshot_percentage": "", "clutch_success_percentage": "", "agents_played": ["raze", "reyna"], "kmax": "19", "kills": "55", "deaths": "66", "assists": "15", "fk": "0", "fd": "0"}, {"player": "Spitfires", "org": "AG", "rounds": "86", "rating": "", "average_combat_score": "176.5", "kill_deaths": "0.84", "kill_assists_survived_traded": "", "average_damage_per_round": "", "kills_per_round": "0.66", "assists_per_round": "0.16", "first_kills_per_round": "", "first_deaths_per_round": "", "headshot_percentage": "", "clutch_success_percentage": "", "agents_played": ["cypher", "jett", "killjoy"], "kmax": "21", "kills": "57", "deaths": "68", "assists": "14", "fk": "0", "fd": "0"}, {"player": "whzy", "org": "BLG", "rounds": "202", "rating": "", "average_combat_score": "244.8", "kill_deaths": "1.15", "kill_assists_survived_traded": "", "average_damage_per_round": "", "kills_per_round": "0.85", "assists_per_round": "0.19", "first_kills_per_round": "", "first_deaths_per_round": "", "headshot_percentage": "", "clutch_success_percentage": "", "agents_played": ["jett", "raze"], "kmax": "25", "kills": "172", "deaths": "149", "assists": "38", "fk": "0", "fd": "0"}, {"player": "Knight", "org": "BLG", "rounds": "202", "rating": "", "average_combat_score": "223.2", "kill_deaths": "1.15", "kill_assists_survived_traded": "", "average_damage_per_round": "", "kills_per_round": "0.78", "assists_per_round": "0.36", "first_kills_per_round": "", "first_deaths_per_round": "", "headshot_percentage": "", "clutch_success_percentage": "", "agents_played": ["kayo", "killjoy", "breach"], "kmax": "24", "kills": "157", "deaths": "136", "assists": "72", "fk": "0", "fd": "0"}, {"player": "Abo", "org": "TEC", "rounds": "297", "rating": "", "average_combat_score": "197.2", "kill_deaths": "0.92", "kill_assists_survived_traded": "", "average_damage_per_round": "", "kills_per_round": "0.69", "assists_per_round": "0.15", "first_kills_per_round": "", "first_deaths_per_round": "", "headshot_percentage": "", "clutch_success_percentage": "", "agents_played": ["raze", "jett"], "kmax": "28", "kills": "206", "deaths": "225", "assists": "45", "fk": "0", "fd": "0"}, {"player": "Yosemite", "org": "BLG", "rounds": "202", "rating": "", "average_combat_score": "222.3", "kill_deaths": "1.20", "kill_assists_survived_traded": "", "average_damage_per_round": "", "kills_per_round": "0.77", "assists_per_round": "0.30", "first_kills_per_round": "", "first_deaths_per_round": "", "headshot_percentage": "", "clutch_success_percentage": "", "agents_played": ["killjoy", "viper", "cypher"], "kmax": "28", "kills": "156", "deaths": "130", "assists": "60", "fk": "0", "fd": "0"}, {"player": "B3ar", "org": "BLG", "rounds": "202", "rating": "", "average_combat_score": "132.4", "kill_deaths": "0.74", "kill_assists_survived_traded": "", "average_damage_per_round": "", "kills_per_round": "0.47", "assists_per_round": "0.44", "first_kills_per_round": "", "first_deaths_per_round": "", "headshot_percentage": "", "clutch_success_percentage": "", "agents_played": ["omen", "harbor", "brimstone"], "kmax": "14", "kills": "95", "deaths": "129", "assists": "88", "fk": "0", "fd": "0"}, {"player": "pl1xx", "org": "WOL", "rounds": "157", "rating": "", "average_combat_score": "216.0", "kill_deaths": "1.04", "kill_assists_survived_traded": "", "average_damage_per_round": "", "kills_per_round": "0.75", "assists_per_round": "0.35", "first_kills_per_round": "", "first_deaths_per_round": "", "headshot_percentage": "", "clutch_success_percentage": "", "agents_played": ["kayo", "viper", "yoru"], "kmax": "21", "kills": "117", "deaths": "112", "assists": "55", "fk": "0", "fd": "0"}, {"player": "Spring", "org": "WOL", "rounds": "157", "rating": "", "average_combat_score": "201.0", "kill_deaths": "1.05", "kill_assists_survived_traded": "", "average_damage_per_round": "", "kills_per_round": "0.71", "assists_per_round": "0.21", "first_kills_per_round": "", "first_deaths_per_round": "", "headshot_percentage": "", "clutch_success_percentage": "", "agents_played": ["jett", "omen", "raze"], "kmax": "26", "kills": "111", "deaths": "106", "assists": "33", "fk": "0", "fd": "0"}, {"player": "aluba", "org": "WOL", "rounds": "157", "rating": "", "average_combat_score": "189.1", "kill_deaths": "0.99", "kill_assists_survived_traded": "", "average_damage_per_round": "", "kills_per_round": "0.66", "assists_per_round": "0.38", "first_kills_per_round": "", "first_deaths_per_round": "", "headshot_percentage": "", "clutch_success_percentage": "", "agents_played": ["omen", "killjoy", "skye"], "kmax": "17", "kills": "103", "deaths": "104", "assists": "60", "fk": "0", "fd": "0"}, {"player": "coldfish", "org": "WOL", "rounds": "157", "rating": "", "average_combat_score": "183.4", "kill_deaths": "1.12", "kill_assists_survived_traded": "", "average_damage_per_round": "", "kills_per_round": "0.69", "assists_per_round": "0.22", "first_kills_per_round": "", "first_deaths_per_round": "", "headshot_percentage": "", "clutch_success_percentage": "", "agents_played": ["sova", "viper"], "kmax": "21", "kills": "109", "deaths": "97", "assists": "34", "fk": "0", "fd": "0"}, {"player": "Yuicaw", "org": "WOL", "rounds": "157", "rating": "", "average_combat_score": "211.0", "kill_deaths": "1.01", "kill_assists_survived_traded": "", "average_damage_per_round": "", "kills_per_round": "0.72", "assists_per_round": "0.30", "first_kills_per_round": "", "first_deaths_per_round": "", "headshot_percentage": "", "clutch_success_percentage": "", "agents_played": ["cypher", "raze"], "kmax": "19", "kills": "113", "deaths": "112", "assists": "47", "fk": "0", "fd": "0"}, {"player": "Haodong", "org": "EDG", "rounds": "211", "rating": "", "average_combat_score": "151.7", "kill_deaths": "0.79", "kill_assists_survived_traded": "", "average_damage_per_round": "", "kills_per_round": "0.53", "assists_per_round": "0.35", "first_kills_per_round": "", "first_deaths_per_round": "", "headshot_percentage": "", "clutch_success_percentage": "", "agents_played": ["cypher", "omen", "viper"], "kmax": "20", "kills": "111", "deaths": "140", "assists": "74", "fk": "0", "fd": "0"}, {"player": "ZmjjKK", "org": "EDG", "rounds": "211", "rating": "", "average_combat_score": "267.8", "kill_deaths": "1.15", "kill_assists_survived_traded": "", "average_damage_per_round": "", "kills_per_round": "0.90", "assists_per_round": "0.22", "first_kills_per_round": "", "first_deaths_per_round": "", "headshot_percentage": "", "clutch_success_percentage": "", "agents_played": ["kayo", "jett", "raze"], "kmax": "30", "kills": "189", "deaths": "164", "assists": "47", "fk": "0", "fd": "0"}, {"player": "nobody", "org": "EDG", "rounds": "211", "rating": "", "average_combat_score": "213.2", "kill_deaths": "1.09", "kill_assists_survived_traded": "", "average_damage_per_round": "", "kills_per_round": "0.75", "assists_per_round": "0.25", "first_kills_per_round": "", "first_deaths_per_round": "", "headshot_percentage": "", "clutch_success_percentage": "", "agents_played": ["sova", "skye"], "kmax": "27", "kills": "159", "deaths": "146", "assists": "53", "fk": "0", "fd": "0"}, {"player": "CHICHOO", "org": "EDG", "rounds": "211", "rating": "", "average_combat_score": "211.9", "kill_deaths": "1.11", "kill_assists_survived_traded": "", "average_damage_per_round": "", "kills_per_round": "0.76", "assists_per_round": "0.23", "first_kills_per_round": "", "first_deaths_per_round": "", "headshot_percentage": "", "clutch_success_percentage": "", "agents_played": ["brimstone", "viper", "cypher"], "kmax": "24", "kills": "161", "deaths": "145", "assists": "49", "fk": "0", "fd": "0"}, {"player": "kawaii", "org": "TEC", "rounds": "297", "rating": "", "average_combat_score": "193.7", "kill_deaths": "0.98", "kill_assists_survived_traded": "", "average_damage_per_round": "", "kills_per_round": "0.70", "assists_per_round": "0.38", "first_kills_per_round": "", "first_deaths_per_round": "", "headshot_percentage": "", "clutch_success_percentage": "", "agents_played": ["omen", "brimstone", "viper"], "kmax": "30", "kills": "207", "deaths": "211", "assists": "113", "fk": "0", "fd": "0"}, {"player": "LockM", "org": "TEC", "rounds": "297", "rating": "", "average_combat_score": "181.6", "kill_deaths": "0.86", "kill_assists_survived_traded": "", "average_damage_per_round": "", "kills_per_round": "0.62", "assists_per_round": "0.27", "first_kills_per_round": "", "first_deaths_per_round": "", "headshot_percentage": "", "clutch_success_percentage": "", "agents_played": ["viper", "sova"], "kmax": "25", "kills": "184", "deaths": "215", "assists": "80", "fk": "0", "fd": "0"}, {"player": "Flex1n", "org": "TE", "rounds": "336", "rating": "", "average_combat_score": "205.1", "kill_deaths": "1.03", "kill_assists_survived_traded": "", "average_damage_per_round": "", "kills_per_round": "0.71", "assists_per_round": "0.39", "first_kills_per_round": "", "first_deaths_per_round": "", "headshot_percentage": "", "clutch_success_percentage": "", "agents_played": ["omen", "viper"], "kmax": "27", "kills": "240", "deaths": "232", "assists": "130", "fk": "0", "fd": "0"}, {"player": "Autumn", "org": "FPX", "rounds": "250", "rating": "", "average_combat_score": "215.5", "kill_deaths": "1.09", "kill_assists_survived_traded": "", "average_damage_per_round": "", "kills_per_round": "0.74", "assists_per_round": "0.18", "first_kills_per_round": "", "first_deaths_per_round": "", "headshot_percentage": "", "clutch_success_percentage": "", "agents_played": ["raze", "phoenix", "jett"], "kmax": "25", "kills": "186", "deaths": "170", "assists": "45", "fk": "0", "fd": "0"}, {"player": "YOU", "org": "TE", "rounds": "336", "rating": "", "average_combat_score": "189.5", "kill_deaths": "1.03", "kill_assists_survived_traded": "", "average_damage_per_round": "", "kills_per_round": "0.67", "assists_per_round": "0.32", "first_kills_per_round": "", "first_deaths_per_round": "", "headshot_percentage": "", "clutch_success_percentage": "", "agents_played": ["killjoy", "sova", "skye"], "kmax": "24", "kills": "224", "deaths": "218", "assists": "108", "fk": "0", "fd": "0"}, {"player": "heybay", "org": "TE", "rounds": "336", "rating": "", "average_combat_score": "190.1", "kill_deaths": "1.02", "kill_assists_survived_traded": "", "average_damage_per_round": "", "kills_per_round": "0.66", "assists_per_round": "0.44", "first_kills_per_round": "", "first_deaths_per_round": "", "headshot_percentage": "", "clutch_success_percentage": "", "agents_played": ["kayo", "breach", "brimstone"], "kmax": "20", "kills": "221", "deaths": "217", "assists": "148", "fk": "0", "fd": "0"}, {"player": "Kai", "org": "TE", "rounds": "336", "rating": "", "average_combat_score": "221.7", "kill_deaths": "1.26", "kill_assists_survived_traded": "", "average_damage_per_round": "", "kills_per_round": "0.82", "assists_per_round": "0.15", "first_kills_per_round": "", "first_deaths_per_round": "", "headshot_percentage": "", "clutch_success_percentage": "", "agents_played": ["jett", "cypher", "killjoy"], "kmax": "31", "kills": "277", "deaths": "220", "assists": "52", "fk": "0", "fd": "0"}, {"player": "LuoK1ng", "org": "TYL", "rounds": "81", "rating": "", "average_combat_score": "208.5", "kill_deaths": "1.02", "kill_assists_survived_traded": "", "average_damage_per_round": "", "kills_per_round": "0.75", "assists_per_round": "0.30", "first_kills_per_round": "", "first_deaths_per_round": "", "headshot_percentage": "", "clutch_success_percentage": "", "agents_played": ["omen"], "kmax": "23", "kills": "61", "deaths": "60", "assists": "24", "fk": "0", "fd": "0"}, {"player": "Ninebody", "org": "TYL", "rounds": "81", "rating": "", "average_combat_score": "232.3", "kill_deaths": "1.03", "kill_assists_survived_traded": "", "average_damage_per_round": "", "kills_per_round": "0.78", "assists_per_round": "0.38", "first_kills_per_round": "", "first_deaths_per_round": "", "headshot_percentage": "", "clutch_success_percentage": "", "agents_played": ["phoenix", "raze"], "kmax": "22", "kills": "63", "deaths": "61", "assists": "31", "fk": "0", "fd": "0"}, {"player": "ICEKING", "org": "TYL", "rounds": "81", "rating": "", "average_combat_score": "208.5", "kill_deaths": "0.89", "kill_assists_survived_traded": "", "average_damage_per_round": "", "kills_per_round": "0.69", "assists_per_round": "0.31", "first_kills_per_round": "", "first_deaths_per_round": "", "headshot_percentage": "", "clutch_success_percentage": "", "agents_played": ["cypher", "kayo", "viper"], "kmax": "23", "kills": "56", "deaths": "63", "assists": "25", "fk": "0", "fd": "0"}, {"player": "AAK", "org": "TYL", "rounds": "81", "rating": "", "average_combat_score": "173.0", "kill_deaths": "0.83", "kill_assists_survived_traded": "", "average_damage_per_round": "", "kills_per_round": "0.67", "assists_per_round": "0.19", "first_kills_per_round": "", "first_deaths_per_round": "", "headshot_percentage": "", "clutch_success_percentage": "", "agents_played": ["jett", "cypher"], "kmax": "19", "kills": "54", "deaths": "65", "assists": "15", "fk": "0", "fd": "0"}, {"player": "hfmi0dzjc9z7", "org": "TYL", "rounds": "81", "rating": "", "average_combat_score": "152.5", "kill_deaths": "0.62", "kill_assists_survived_traded": "", "average_damage_per_round": "", "kills_per_round": "0.51", "assists_per_round": "0.26", "first_kills_per_round": "", "first_deaths_per_round": "", "headshot_percentage": "", "clutch_success_percentage": "", "agents_played": ["sova", "gekko", "skye"], "kmax": "13", "kills": "41", "deaths": "66", "assists": "21", "fk": "0", "fd": "0"}, {"player": "AAAAY", "org": "FPX", "rounds": "250", "rating": "", "average_combat_score": "216.6", "kill_deaths": "1.16", "kill_assists_survived_traded": "", "average_damage_per_round": "", "kills_per_round": "0.80", "assists_per_round": "0.20", "first_kills_per_round": "", "first_deaths_per_round": "", "headshot_percentage": "", "clutch_success_percentage": "", "agents_played": ["gekko", "sova", "fade"], "kmax": "26", "kills": "201", "deaths": "174", "assists": "51", "fk": "0", "fd": "0"}, {"player": "BerLIN", "org": "FPX", "rounds": "250", "rating": "", "average_combat_score": "185.8", "kill_deaths": "1.00", "kill_assists_survived_traded": "", "average_damage_per_round": "", "kills_per_round": "0.66", "assists_per_round": "0.34", "first_kills_per_round": "", "first_deaths_per_round": "", "headshot_percentage": "", "clutch_success_percentage": "", "agents_played": ["omen", "harbor", "astra"], "kmax": "26", "kills": "165", "deaths": "165", "assists": "84", "fk": "0", "fd": "0"}, {"player": "Lysoar", "org": "FPX", "rounds": "250", "rating": "", "average_combat_score": "169.4", "kill_deaths": "0.92", "kill_assists_survived_traded": "", "average_damage_per_round": "", "kills_per_round": "0.59", "assists_per_round": "0.25", "first_kills_per_round": "", "first_deaths_per_round": "", "headshot_percentage": "", "clutch_success_percentage": "", "agents_played": ["viper", "cypher"], "kmax": "20", "kills": "147", "deaths": "159", "assists": "63", "fk": "0", "fd": "0"}, {"player": "Life", "org": "FPX", "rounds": "250", "rating": "", "average_combat_score": "235.5", "kill_deaths": "1.14", "kill_assists_survived_traded": "", "average_damage_per_round": "", "kills_per_round": "0.84", "assists_per_round": "0.17", "first_kills_per_round": "", "first_deaths_per_round": "", "headshot_percentage": "", "clutch_success_percentage": "", "agents_played": ["chamber", "yoru", "jett"], "kmax": "28", "kills": "209", "deaths": "184", "assists": "43", "fk": "0", "fd": "0"}, {"player": "Rb", "org": "TEC", "rounds": "297", "rating": "", "average_combat_score": "233.9", "kill_deaths": "1.20", "kill_assists_survived_traded": "", "average_damage_per_round": "", "kills_per_round": "0.84", "assists_per_round": "0.24", "first_kills_per_round": "", "first_deaths_per_round": "", "headshot_percentage": "", "clutch_success_percentage": "", "agents_played": ["fade", "cypher", "killjoy"], "kmax": "29", "kills": "250", "deaths": "209", "assists": "70", "fk": "0", "fd": "0"}, {"player": "PangH", "org": "NOVA", "rounds": "124", "rating": "", "average_combat_score": "156.3", "kill_deaths": "0.69", "kill_assists_survived_traded": "", "average_damage_per_round": "", "kills_per_round": "0.54", "assists_per_round": "0.13", "first_kills_per_round": "", "first_deaths_per_round": "", "headshot_percentage": "", "clutch_success_percentage": "", "agents_played": ["killjoy", "jett", "raze"], "kmax": "25", "kills": "67", "deaths": "97", "assists": "16", "fk": "0", "fd": "0"}, {"player": "o0o0o", "org": "NOVA", "rounds": "124", "rating": "", "average_combat_score": "186.7", "kill_deaths": "0.87", "kill_assists_survived_traded": "", "average_damage_per_round": "", "kills_per_round": "0.69", "assists_per_round": "0.27", "first_kills_per_round": "", "first_deaths_per_round": "", "headshot_percentage": "", "clutch_success_percentage": "", "agents_played": ["raze", "breach", "viper"], "kmax": "23", "kills": "86", "deaths": "99", "assists": "34", "fk": "0", "fd": "0"}, {"player": "OBONE", "org": "NOVA", "rounds": "124", "rating": "", "average_combat_score": "162.8", "kill_deaths": "0.75", "kill_assists_survived_traded": "", "average_damage_per_round": "", "kills_per_round": "0.56", "assists_per_round": "0.34", "first_kills_per_round": "", "first_deaths_per_round": "", "headshot_percentage": "", "clutch_success_percentage": "", "agents_played": ["omen"], "kmax": "18", "kills": "70", "deaths": "93", "assists": "42", "fk": "0", "fd": "0"}, {"player": "CB", "org": "NOVA", "rounds": "124", "rating": "", "average_combat_score": "173.7", "kill_deaths": "0.73", "kill_assists_survived_traded": "", "average_damage_per_round": "", "kills_per_round": "0.56", "assists_per_round": "0.38", "first_kills_per_round": "", "first_deaths_per_round": "", "headshot_percentage": "", "clutch_success_percentage": "", "agents_played": ["breach", "fade", "sova"], "kmax": "17", "kills": "69", "deaths": "94", "assists": "47", "fk": "0", "fd": "0"}, {"player": "GuanG", "org": "NOVA", "rounds": "124", "rating": "", "average_combat_score": "243.3", "kill_deaths": "1.03", "kill_assists_survived_traded": "", "average_damage_per_round": "", "kills_per_round": "0.82", "assists_per_round": "0.22", "first_kills_per_round": "", "first_deaths_per_round": "", "headshot_percentage": "", "clutch_success_percentage": "", "agents_played": ["jett", "neon", "killjoy"], "kmax": "29", "kills": "102", "deaths": "99", "assists": "27", "fk": "0", "fd": "0"}, {"player": "stew", "org": "JDG", "rounds": "163", "rating": "", "average_combat_score": "265.9", "kill_deaths": "1.32", "kill_assists_survived_traded": "", "average_damage_per_round": "", "kills_per_round": "0.93", "assists_per_round": "0.18", "first_kills_per_round": "", "first_deaths_per_round": "", "headshot_percentage": "", "clutch_success_percentage": "", "agents_played": ["raze", "jett"], "kmax": "35", "kills": "152", "deaths": "115", "assists": "30", "fk": "0", "fd": "0"}, {"player": "Viva", "org": "JDG", "rounds": "163", "rating": "", "average_combat_score": "214.1", "kill_deaths": "1.21", "kill_assists_survived_traded": "", "average_damage_per_round": "", "kills_per_round": "0.75", "assists_per_round": "0.23", "first_kills_per_round": "", "first_deaths_per_round": "", "headshot_percentage": "", "clutch_success_percentage": "", "agents_played": ["viper", "sova"], "kmax": "22", "kills": "122", "deaths": "101", "assists": "38", "fk": "0", "fd": "0"}, {"player": "jkuro", "org": "JDG", "rounds": "163", "rating": "", "average_combat_score": "180.6", "kill_deaths": "0.87", "kill_assists_survived_traded": "", "average_damage_per_round": "", "kills_per_round": "0.64", "assists_per_round": "0.23", "first_kills_per_round": "", "first_deaths_per_round": "", "headshot_percentage": "", "clutch_success_percentage": "", "agents_played": ["fade", "skye", "viper"], "kmax": "21", "kills": "104", "deaths": "120", "assists": "38", "fk": "0", "fd": "0"}, {"player": "YiHao", "org": "JDG", "rounds": "163", "rating": "", "average_combat_score": "155.9", "kill_deaths": "0.82", "kill_assists_survived_traded": "", "average_damage_per_round": "", "kills_per_round": "0.56", "assists_per_round": "0.35", "first_kills_per_round": "", "first_deaths_per_round": "", "headshot_percentage": "", "clutch_success_percentage": "", "agents_played": ["astra", "brimstone", "harbor"], "kmax": "22", "kills": "91", "deaths": "111", "assists": "57", "fk": "0", "fd": "0"}, {"player": "MarT1n", "org": "JDG", "rounds": "163", "rating": "", "average_combat_score": "199.1", "kill_deaths": "0.93", "kill_assists_survived_traded": "", "average_damage_per_round": "", "kills_per_round": "0.67", "assists_per_round": "0.13", "first_kills_per_round": "", "first_deaths_per_round": "", "headshot_percentage": "", "clutch_success_percentage": "", "agents_played": ["killjoy", "viper"], "kmax": "22", "kills": "109", "deaths": "117", "assists": "22", "fk": "0", "fd": "0"}, {"player": "QiuYe", "org": "TEC", "rounds": "297", "rating": "", "average_combat_score": "166.4", "kill_deaths": "0.74", "kill_assists_survived_traded": "", "average_damage_per_round": "", "kills_per_round": "0.57", "assists_per_round": "0.30", "first_kills_per_round": "", "first_deaths_per_round": "", "headshot_percentage": "", "clutch_success_percentage": "", "agents_played": ["killjoy", "skye", "harbor"], "kmax": "23", "kills": "170", "deaths": "229", "assists": "90", "fk": "0", "fd": "0"}, {"player": "Smoggy", "org": "EDG", "rounds": "211", "rating": "", "average_combat_score": "188.2", "kill_deaths": "0.99", "kill_assists_survived_traded": "", "average_damage_per_round": "", "kills_per_round": "0.66", "assists_per_round": "0.46", "first_kills_per_round": "", "first_deaths_per_round": "", "headshot_percentage": "", "clutch_success_percentage": "", "agents_played": ["raze", "breach", "kayo"], "kmax": "20", "kills": "139", "deaths": "140", "assists": "97", "fk": "0", "fd": "0"}]